spacy_fi_experimental_web_md/__init__.py
spacy_fi_experimental_web_md/fi.py
spacy_fi_experimental_web_md/meta.json
spacy_fi_experimental_web_md/fi_experimental_web_md-0.15.0/README.md
spacy_fi_experimental_web_md/fi_experimental_web_md-0.15.0/config.cfg
spacy_fi_experimental_web_md/fi_experimental_web_md-0.15.0/meta.json
spacy_fi_experimental_web_md/fi_experimental_web_md-0.15.0/tokenizer
spacy_fi_experimental_web_md/fi_experimental_web_md-0.15.0/attribute_ruler/patterns
spacy_fi_experimental_web_md/fi_experimental_web_md-0.15.0/lemmatizer/lookups/lookups.bin
spacy_fi_experimental_web_md/fi_experimental_web_md-0.15.0/morphologizer/cfg
spacy_fi_experimental_web_md/fi_experimental_web_md-0.15.0/morphologizer/model
spacy_fi_experimental_web_md/fi_experimental_web_md-0.15.0/ner/cfg
spacy_fi_experimental_web_md/fi_experimental_web_md-0.15.0/ner/model
spacy_fi_experimental_web_md/fi_experimental_web_md-0.15.0/ner/moves
spacy_fi_experimental_web_md/fi_experimental_web_md-0.15.0/parser/cfg
spacy_fi_experimental_web_md/fi_experimental_web_md-0.15.0/parser/model
spacy_fi_experimental_web_md/fi_experimental_web_md-0.15.0/parser/moves
spacy_fi_experimental_web_md/fi_experimental_web_md-0.15.0/tagger/cfg
spacy_fi_experimental_web_md/fi_experimental_web_md-0.15.0/tagger/model
spacy_fi_experimental_web_md/fi_experimental_web_md-0.15.0/tok2vec/cfg
spacy_fi_experimental_web_md/fi_experimental_web_md-0.15.0/tok2vec/model
spacy_fi_experimental_web_md/fi_experimental_web_md-0.15.0/vocab/key2row
spacy_fi_experimental_web_md/fi_experimental_web_md-0.15.0/vocab/lookups.bin
spacy_fi_experimental_web_md/fi_experimental_web_md-0.15.0/vocab/strings.json
spacy_fi_experimental_web_md/fi_experimental_web_md-0.15.0/vocab/vectors
spacy_fi_experimental_web_md/fi_experimental_web_md-0.15.0/vocab/vectors.cfg
spacy_fi_experimental_web_md-0.15.0.dist-info/METADATA
spacy_fi_experimental_web_md-0.15.0.dist-info/WHEEL
spacy_fi_experimental_web_md-0.15.0.dist-info/entry_points.txt
spacy_fi_experimental_web_md-0.15.0.dist-info/top_level.txt
spacy_fi_experimental_web_md-0.15.0.dist-info/RECORD
